LICENSE.txt
MANIFEST.in
README.rst
pysftp.py
requirements-dev.txt
setup.py
docs/authors.rst
docs/changes.rst
docs/conf.py
docs/contributing.rst
docs/index.rst
docs/pysftp.rst
pysftp.egg-info/PKG-INFO
pysftp.egg-info/SOURCES.txt
pysftp.egg-info/dependency_links.txt
pysftp.egg-info/requires.txt
pysftp.egg-info/top_level.txt