Metadata-Version: 1.1
Name: pysftp
Version: 0.2.4
Summary: A friendly face on SFTP
Home-page: https://bitbucket.org/dundeemt/pysftp
Author: Jeff Hinrichs
Author-email: jeffh@dundeemt.com
License: BSD
Download-URL: https://pypi.python.org/pypi/pysftp
Keywords: sftp ssh ftp internet
Platform: any
Classifier: Development Status :: 4 - Beta
Classifier: License :: OSI Approved :: BSD License
Classifier: Programming Language :: Python
Classifier: Programming Language :: Python :: 2
Classifier: Programming Language :: Python :: 2.7
Classifier: Programming Language :: Python :: 3
Classifier: Programming Language :: Python :: 3.2
Classifier: Programming Language :: Python :: 3.3
Classifier: Programming Language :: Python :: 3.4
Classifier: Programming Language :: Python :: Implementation :: CPython
